src/__init__.py
src/core.py
src/test_core.py
mkdocs_techdocs_bandicoot-1.1.9.dist-info/LICENSE
mkdocs_techdocs_bandicoot-1.1.9.dist-info/METADATA
mkdocs_techdocs_bandicoot-1.1.9.dist-info/WHEEL
mkdocs_techdocs_bandicoot-1.1.9.dist-info/entry_points.txt
mkdocs_techdocs_bandicoot-1.1.9.dist-info/top_level.txt
mkdocs_techdocs_bandicoot-1.1.9.dist-info/RECORD
