Metadata-Version: 2.1
Name: mkdocs-techdocs-bandicoot
Version: 1.1.9
Summary: The core MkDocs plugin used by Bandicoot's TechDocs as a wrapper around multiple MkDocs plugins and Python Markdown extensions
Home-page: https://github.com/kaemonisland/mkdocs-techdocs-core
Author: TechDocs Core Bandicoot
Author-email: kaemonlovendahl@outlook.com
License: Apache-2.0
Keywords: mkdocs
Platform: UNKNOWN
Classifier: Development Status :: 3 - Alpha
Classifier: Intended Audience :: Developers
Classifier: Intended Audience :: Information Technology
Classifier: License :: OSI Approved :: Apache Software License
Classifier: Programming Language :: Python
Classifier: Programming Language :: Python :: 3 :: Only
Classifier: Programming Language :: Python :: 3.12
Requires-Python: >=3.12
Requires-Dist: mkdocs >=1.2.2
Requires-Dist: Markdown <3.4,>=3.2
Requires-Dist: mkdocs-material ==8.1.11
Requires-Dist: mkdocs-monorepo-plugin ==1.0.4
Requires-Dist: plantuml-markdown ==3.5.1
Requires-Dist: markdown-inline-graphviz-extension ==1.1.1
Requires-Dist: mdx-truly-sane-lists ==1.3
Requires-Dist: pygments ==2.10
Requires-Dist: pymdown-extensions ==9.3
